{
  "id": "clock_return",
  "lines": [
	{
	  "speaker": "旁白",
	  "text": "旧闹钟安静地放在那里。塑料外壳泛黄，秒针一格一格地跳——和2008年看到的一模一样。"
	},
	{
	  "speaker": "我",
	  "text": "之前就是碰了它……"
	},
	{
	  "speaker": "旁白",
	  "text": "深吸一口气。手指伸向闹钟。"
	},
	{
	  "speaker": "旁白",
	  "text": "触碰的瞬间——世界开始旋转。墙纸褪色，液晶屏坍缩成大屁股电视。闹钟在掌心里发烫。"
	},
	{
	  "speaker": "我",
	  "text": "真的是它……这个闹钟，连接着两个时间。"
	},
	{
	  "speaker": "旁白",
	  "text": "刚才的2026年，和等在前面的2008年——是同一个房子。同一个客厅，同一面墙，同一道裂缝。"
	},
	{
	  "speaker": "我",
	  "text": "我不是在做梦。我是在这栋老房子里，两个不同的时间之间——来回穿越。"
	},
	{
	  "speaker": "旁白",
	  "text": "日历往回翻。世界在旋转中重组。2008年的光从裂缝里涌了出来——",
	  "event": "travel_to_2008"
	}
  ]
}
